famodels/__init__.py
famodels/direction.py
famodels/email_subscriber.py
famodels/investor.py
famodels/investor_statement.py
famodels/order.py
famodels/order_type.py
famodels/person.py
famodels/qualified_signal.py
famodels/raw_signal.py
famodels/rejected_signal.py
famodels/signal_provider.py
famodels/status_of_signal.py
famodels/strategy.py
famodels/trade.py
famodels/virtual_order.py
famodels/exchange/__init__.py
famodels/exchange/connection_event.py
famodels/exchange/exchange_connection_event.py
famodels/fund/__init__.py
famodels/fund/fund.py
famodels/market/__init__.py
famodels/market/public_trade.py
fa_models-1.1.20.dist-info/METADATA
fa_models-1.1.20.dist-info/WHEEL
fa_models-1.1.20.dist-info/top_level.txt
fa_models-1.1.20.dist-info/RECORD
