Metadata-Version: 2.1
Name: fa-models
Version: 1.1.20
Summary: A simple library of trading models.
Author-email: Brayan Svan <brayan@freyaalpha.com>
Project-URL: Homepage, https://github.com/svabra/fa-models
Keywords: finance,trading,models
Classifier: License :: OSI Approved :: MIT License
Classifier: Programming Language :: Python
Requires-Python: >=3.9
Requires-Dist: sqlmodel
Requires-Dist: tomli ; python_version < "3.11"
Provides-Extra: dev
Requires-Dist: black ; extra == 'dev'
Requires-Dist: bumpver ; extra == 'dev'
Requires-Dist: isort ; extra == 'dev'
Requires-Dist: pip-tools ; extra == 'dev'
Requires-Dist: pytest ; extra == 'dev'
